leitor_pdf/__init__.py
leitor_pdf/cli.py
leitor_pdf/exceptions.py
leitor_pdf/main.py
leitor_pdf-0.1.4.dist-info/entry_points.txt
leitor_pdf-0.1.4.dist-info/LICENSE
leitor_pdf-0.1.4.dist-info/METADATA
leitor_pdf-0.1.4.dist-info/WHEEL
leitor_pdf-0.1.4.dist-info/RECORD
